wave_venture/__init__.py
wave_venture/__version__.py
wave_venture/config.py
wave_venture/interface.py
wave_venture/plotting.py
wave_venture/serializer.py
wave_venture/utils.py
wave_venture/resources/__init__.py
wave_venture/resources/wave-venture-logo.png
wave_venture-0.0.48.dist-info/METADATA
wave_venture-0.0.48.dist-info/WHEEL
wave_venture-0.0.48.dist-info/top_level.txt
wave_venture-0.0.48.dist-info/RECORD
